odoo/addons/sale_stock_mto_as_mts_orderpoint/README.rst
odoo/addons/sale_stock_mto_as_mts_orderpoint/__init__.py
odoo/addons/sale_stock_mto_as_mts_orderpoint/__manifest__.py
odoo/addons/sale_stock_mto_as_mts_orderpoint/data/stock_data.xml
odoo/addons/sale_stock_mto_as_mts_orderpoint/i18n/it.po
odoo/addons/sale_stock_mto_as_mts_orderpoint/i18n/sale_stock_mto_as_mts_orderpoint.pot
odoo/addons/sale_stock_mto_as_mts_orderpoint/migrations/14.0.1.1.0/post-migrate.py
odoo/addons/sale_stock_mto_as_mts_orderpoint/models/__init__.py
odoo/addons/sale_stock_mto_as_mts_orderpoint/models/product.py
odoo/addons/sale_stock_mto_as_mts_orderpoint/models/sale_order.py
odoo/addons/sale_stock_mto_as_mts_orderpoint/models/stock_move.py
odoo/addons/sale_stock_mto_as_mts_orderpoint/models/stock_warehouse.py
odoo/addons/sale_stock_mto_as_mts_orderpoint/readme/CONFIGURATION.rst
odoo/addons/sale_stock_mto_as_mts_orderpoint/readme/CONTRIBUTORS.rst
odoo/addons/sale_stock_mto_as_mts_orderpoint/readme/CREDITS.rst
odoo/addons/sale_stock_mto_as_mts_orderpoint/readme/DESCRIPTION.rst
odoo/addons/sale_stock_mto_as_mts_orderpoint/readme/ROADMAP.rst
odoo/addons/sale_stock_mto_as_mts_orderpoint/static/description/icon.png
odoo/addons/sale_stock_mto_as_mts_orderpoint/static/description/index.html
odoo/addons/sale_stock_mto_as_mts_orderpoint/tests/__init__.py
odoo/addons/sale_stock_mto_as_mts_orderpoint/tests/test_sale_stock_mto_as_mts_orderpoint.py
odoo/addons/sale_stock_mto_as_mts_orderpoint/views/stock_warehouse_views.xml
odoo14_addon_sale_stock_mto_as_mts_orderpoint-14.0.1.1.1.dist-info/METADATA
odoo14_addon_sale_stock_mto_as_mts_orderpoint-14.0.1.1.1.dist-info/WHEEL
odoo14_addon_sale_stock_mto_as_mts_orderpoint-14.0.1.1.1.dist-info/top_level.txt
odoo14_addon_sale_stock_mto_as_mts_orderpoint-14.0.1.1.1.dist-info/RECORD
